examples/__init__.py
examples/about.py
rclone_api/__init__.py
rclone_api/api.py
rclone_api/dto.py
rclone_api/exceptions.py
rclone_api/bin/rclone.exe
tests/test_exceptions.py
tests/test_rclone.py
rclone_bin_api-1.0.2.dist-info/METADATA
rclone_bin_api-1.0.2.dist-info/WHEEL
rclone_bin_api-1.0.2.dist-info/top_level.txt
rclone_bin_api-1.0.2.dist-info/RECORD
