Metadata-Version: 2.4
Name: rclone-bin-api
Version: 1.0.2
Summary: Rclone API for Python including the Rclone binaries.
Author-email: Michael G <me@mgineer85.de>
Maintainer-email: Michael G <me@mgineer85.de>
License-Expression: MIT
Project-URL: Repository, https://github.com/mgineer85/rclone-bin-api
Keywords: rclone
Classifier: Programming Language :: Python :: 3
Classifier: Programming Language :: Python :: 3.11
Classifier: Programming Language :: Python :: 3.12
Classifier: Programming Language :: Python :: 3.13
Classifier: Programming Language :: Python :: 3.14
Requires-Python: >=3.11
